odoo/addons/purchase_order_vendor_product/README.rst
odoo/addons/purchase_order_vendor_product/__init__.py
odoo/addons/purchase_order_vendor_product/__manifest__.py
odoo/addons/purchase_order_vendor_product/i18n/it.po
odoo/addons/purchase_order_vendor_product/i18n/purchase_order_vendor_product.pot
odoo/addons/purchase_order_vendor_product/models/__init__.py
odoo/addons/purchase_order_vendor_product/models/product_product.py
odoo/addons/purchase_order_vendor_product/readme/CONTRIBUTORS.rst
odoo/addons/purchase_order_vendor_product/readme/DESCRIPTION.rst
odoo/addons/purchase_order_vendor_product/readme/HISTORY.rst
odoo/addons/purchase_order_vendor_product/readme/USAGE.rst
odoo/addons/purchase_order_vendor_product/static/description/icon.png
odoo/addons/purchase_order_vendor_product/static/description/index.html
odoo/addons/purchase_order_vendor_product/tests/__init__.py
odoo/addons/purchase_order_vendor_product/tests/test_purchase_order_vendor_product.py
odoo/addons/purchase_order_vendor_product/views/purchase_order.xml
odoo14_addon_purchase_order_vendor_product-14.0.1.1.0.dist-info/METADATA
odoo14_addon_purchase_order_vendor_product-14.0.1.1.0.dist-info/WHEEL
odoo14_addon_purchase_order_vendor_product-14.0.1.1.0.dist-info/top_level.txt
odoo14_addon_purchase_order_vendor_product-14.0.1.1.0.dist-info/RECORD
